Metadata-Version: 1.1
Name: cnn-blocks
Version: 0.0.1
Summary: Construct new CNN architectures using famous CNN blocks
Home-page: https://github.com/mitul01/CNN_Architectures
Author: Mitul Tandon
Author-email: mtandon_be18@thapar.edu
License: MIT
Keywords: python,Machine Learning,Deep Learning,CNN,RESNET,VGG,Inception
Platform: UNKNOWN
Classifier: Development Status :: 5 - Production/Stable
Classifier: Intended Audience :: Education
Classifier: Operating System :: Microsoft :: Windows :: Windows 10
Classifier: License :: OSI Approved :: MIT License
Classifier: Programming Language :: Python :: 3
